hakai_api/__init__.py
hakai_api/client.py
hakai_api/auth/__init__.py
hakai_api/auth/base.py
hakai_api/auth/desktop.py
hakai_api/auth/desktop_callback.html
hakai_api/auth/web.py
hakai_api-2.0.0.dist-info/METADATA
hakai_api-2.0.0.dist-info/WHEEL
hakai_api-2.0.0.dist-info/licenses/LICENSE
hakai_api-2.0.0.dist-info/RECORD
