Metadata-Version: 2.4
Name: hakai_api
Version: 2.0.0
Summary: Get Hakai database resources using http calls
Author-email: Taylor Denouden <taylor.denouden@hakai.org>, Chris Davis <chris.davis@hakai.org>, Nate Rosenstock <nate.rosenstock@hakai.org>, Sam Albers <sam.albers@hakai.org>
Maintainer-email: Taylor Denouden <taylor.denouden@hakai.org>, Sam Albers <sam.albers@hakai.org>
License-Expression: MIT
License-File: LICENSE
Requires-Python: >=3.8
Requires-Dist: loguru>=0.7.3
Requires-Dist: pkce>=1.0.3
Requires-Dist: pytz>=2025.2
Requires-Dist: requests-oauthlib>=2.0.0
Requires-Dist: requests>=2.32.3
